endex_factset_fundamentals/__init__.py
endex_factset_fundamentals/_base_client.py
endex_factset_fundamentals/_client.py
endex_factset_fundamentals/_compat.py
endex_factset_fundamentals/_constants.py
endex_factset_fundamentals/_exceptions.py
endex_factset_fundamentals/_files.py
endex_factset_fundamentals/_models.py
endex_factset_fundamentals/_qs.py
endex_factset_fundamentals/_resource.py
endex_factset_fundamentals/_response.py
endex_factset_fundamentals/_streaming.py
endex_factset_fundamentals/_types.py
endex_factset_fundamentals/_version.py
endex_factset_fundamentals/py.typed
endex_factset_fundamentals/_utils/__init__.py
endex_factset_fundamentals/_utils/_logs.py
endex_factset_fundamentals/_utils/_proxy.py
endex_factset_fundamentals/_utils/_reflection.py
endex_factset_fundamentals/_utils/_streams.py
endex_factset_fundamentals/_utils/_sync.py
endex_factset_fundamentals/_utils/_transform.py
endex_factset_fundamentals/_utils/_typing.py
endex_factset_fundamentals/_utils/_utils.py
endex_factset_fundamentals/lib/.keep
endex_factset_fundamentals/resources/__init__.py
endex_factset_fundamentals/resources/batch_processing.py
endex_factset_fundamentals/resources/fundamentals.py
endex_factset_fundamentals/resources/metrics.py
endex_factset_fundamentals/resources/segments.py
endex_factset_fundamentals/resources/company_reports/__init__.py
endex_factset_fundamentals/resources/company_reports/company_reports.py
endex_factset_fundamentals/resources/company_reports/financial_statement.py
endex_factset_fundamentals/resources/company_reports/fundamentals.py
endex_factset_fundamentals/resources/company_reports/profile.py
endex_factset_fundamentals/types/__init__.py
endex_factset_fundamentals/types/batch_processing_result_params.py
endex_factset_fundamentals/types/batch_processing_status_params.py
endex_factset_fundamentals/types/batch_result_response.py
endex_factset_fundamentals/types/batch_status_response.py
endex_factset_fundamentals/types/fundamental_create_params.py
endex_factset_fundamentals-0.1.0a1.dist-info/METADATA
endex_factset_fundamentals-0.1.0a1.dist-info/WHEEL
endex_factset_fundamentals-0.1.0a1.dist-info/licenses/LICENSE
endex_factset_fundamentals-0.1.0a1.dist-info/RECORD
